kghub_downloader/__init__.py
kghub_downloader/download.py
kghub_downloader/download_utils.py
kghub_downloader/elasticsearch.py
kghub_downloader/main.py
kghub_downloader/model.py
kghub_downloader/schemes.py
kghub_downloader/upload.py
kghub_downloader-0.4.4.dist-info/METADATA
kghub_downloader-0.4.4.dist-info/WHEEL
kghub_downloader-0.4.4.dist-info/entry_points.txt
kghub_downloader-0.4.4.dist-info/RECORD
