Metadata-Version: 2.4
Name: kghub-downloader
Version: 0.4.4
Summary: Downloads and caches files for knowledge graph ETL
Author: The Monarch Initiative
Author-email: info@monarchinitiative.org
Requires-Python: >=3.9,<4.0
Classifier: Programming Language :: Python :: 3
Classifier: Programming Language :: Python :: 3.9
Classifier: Programming Language :: Python :: 3.10
Classifier: Programming Language :: Python :: 3.11
Classifier: Programming Language :: Python :: 3.12
Classifier: Programming Language :: Python :: 3.13
Classifier: Programming Language :: Python :: 3.14
Requires-Dist: PyYAML (>5.0,<7.0)
Requires-Dist: boto3 (>=1.34.35)
Requires-Dist: compress-json (>1.0,<2.0)
Requires-Dist: elasticsearch (>7.0,<9.0)
Requires-Dist: gdown (>=4.7.1)
Requires-Dist: google-cloud-storage (>=2.1.0,<3.0.0)
Requires-Dist: pydantic (>=2.9.1,<3.0.0)
Requires-Dist: pydantic-settings (>=2.5.2,<3.0.0)
Requires-Dist: tqdm (>=4.62.3)
Requires-Dist: typer (>=0.12.3)
